Metadata-Version: 2.1
Name: datahubtool
Version: 0.0.2
Summary: Data management toolkit for Duramat Datahub
Home-page: https://github.com/lbj2011/DatahubTool
Author: baojieli
Author-email: lbjxx2011@gmail.com
License: BSD License
Classifier: Programming Language :: Python :: 3
Classifier: Operating System :: OS Independent
License-File: LICENSE
